MANIFEST.in
README.txt
setup.py
docs/HISTORY.txt
two/__init__.py
two.ol.egg-info/PKG-INFO
two.ol.egg-info/SOURCES.txt
two.ol.egg-info/dependency_links.txt
two.ol.egg-info/entry_points.txt
two.ol.egg-info/namespace_packages.txt
two.ol.egg-info/not-zip-safe
two.ol.egg-info/requires.txt
two.ol.egg-info/top_level.txt
two/ol/__init__.py
two/ol/base.py
two/ol/newrelicfix.py
two/ol/util.py
two/ol/views.py
two/ol/tests/__init__.py
two/ol/tests/conftest.py
two/ol/tests/test_dispatcher.py