Metadata-Version: 1.1
Name: two.ol
Version: 0.9
Summary: It takes Two do Django. A django mini framework
Home-page: http://github.com/iivvoo/two.ol
Author: Ivo van der Wijk
Author-email: two@in.m3r.nl
License: BSD
Platform: UNKNOWN
Classifier: Programming Language :: Python
